flask_chip/__init__.py
flask_chip/decorators.py
flask_chip/tokens.py
flask_chip/utils.py
flask_chip-1.0.1.dist-info/DESCRIPTION.rst
flask_chip-1.0.1.dist-info/METADATA
flask_chip-1.0.1.dist-info/RECORD
flask_chip-1.0.1.dist-info/WHEEL
flask_chip-1.0.1.dist-info/metadata.json
flask_chip-1.0.1.dist-info/top_level.txt
