Metadata-Version: 2.0
Name: flask-chip
Version: 1.0.1
Summary: A token generator for Flask apps.
Home-page: https://github.com/s-m-i-t-a/flask_chip
Author: Jindrich K. Smitka
Author-email: smitka.j@gmail.com
License: BSD license
Keywords: flask_chip
Platform: UNKNOWN
Classifier: Development Status :: 2 - Pre-Alpha
Classifier: Intended Audience :: Developers
Classifier: License :: OSI Approved :: BSD License
Classifier: Natural Language :: English
Classifier: Programming Language :: Python :: 2
Classifier: Programming Language :: Python :: 2.7
Classifier: Programming Language :: Python :: 3
Classifier: Programming Language :: Python :: 3.4
Classifier: Programming Language :: Python :: 3.5
Classifier: Programming Language :: Python :: 3.6
Requires-Dist: Flask (>=0.10.1)
Requires-Dist: Werkzeug (>=0.10.4)
Requires-Dist: itsdangerous (>=0.24)
Requires-Dist: blinker (>=1.3)
Requires-Dist: six (>=1.7.3)
Requires-Dist: toolz (>=0.8.2)
Requires-Dist: pyresult (>=1.1.0)
